decisionbandit/__init__.py
decisionbandit/main.py
decisionbandit-0.1.1.dist-info/LICENSE
decisionbandit-0.1.1.dist-info/METADATA
decisionbandit-0.1.1.dist-info/WHEEL
decisionbandit-0.1.1.dist-info/top_level.txt
decisionbandit-0.1.1.dist-info/RECORD
