Metadata-Version: 2.2
Name: decisionbandit
Version: 0.1.1
Summary: A collection of exploration–exploitation strategies for reinforcement learning, including ε-greedy and related policies
Author: Adit Punamiya
Author-email: adit@gmail.com
License: MIT
Requires-Python: >=3.8
License-File: LICENSE
Requires-Dist: numpy
Dynamic: author
Dynamic: author-email
Dynamic: description
Dynamic: description-content-type
Dynamic: license
Dynamic: requires-dist
Dynamic: requires-python
Dynamic: summary
